[
  {
    "name": "ＩＣレコーダ",
    "category": "資源物（小型家電）"
  },
  {
    "name": "ＩＨ調理器",
    "category": "資源物（小型家電）"
  },
  {
    "name": "アイスノン",
    "category": "可燃ごみ"
  },
  {
    "name": "アイスピック",
    "category": "資源物（金属類）"
  },
  {
    "name": "アイロン",
    "category": "資源物（小型家電）"
  },
  {
    "name": "アイロン台",
    "category": "破砕ごみ"
  },
  {
    "name": "アクセサリー（金属製）",
    "category": "資源物（金属類）"
  },
  {
    "name": "油（食用）",
    "category": "可燃ごみ"
  },
  {
    "name": "油で汚れた紙、布",
    "category": "可燃ごみ"
  },
  {
    "name": "油類（灯油・ガソリン・オイル類）",
    "category": "市では収集・処理しません"
  },
  {
    "name": "雨樋（塩ビ製）",
    "category": "破砕ごみ"
  },
  {
    "name": "編み機",
    "category": "資源物（金属類）"
  },
  {
    "name": "網戸（網）",
    "category": "可燃ごみ"
  },
  {
    "name": "網戸（金属枠）",
    "category": "資源物（金属類）"
  },
  {
    "name": "アルバム（のり付き紙製）",
    "category": "可燃ごみ"
  },
  {
    "name": "アルミガード（飛散防止）",
    "category": "資源物（金属類）"
  },
  {
    "name": "アルミ缶（飲料缶）",
    "category": "資源物（飲料缶）"
  },
  {
    "name": "アルミシート",
    "category": "可燃ごみ"
  },
  {
    "name": "アルミ箔、アルミホイル",
    "category": "資源物（金属類）"
  },
  {
    "name": "アンテナ",
    "category": "資源物（小型家電）"
  },
  {
    "name": "衣装ケース（プラスチック製）",
    "category": "破砕ごみ"
  },
  {
    "name": "いす",
    "category": "粗大ごみ指定品目"
  },
  {
    "name": "板ガラス",
    "category": "破砕ごみ"
  },
  {
    "name": "板切れ端",
    "category": "可燃ごみ"
  },
  {
    "name": "一輪車（子供用・運動用）",
    "category": "資源物（金属類）"
  },
  {
    "name": "一輪車（手押し運搬用）",
    "category": "資源物（金属類）"
  },
  {
    "name": "一升びん",
    "category": "資源物（びん）"
  },
  {
    "name": "一斗缶",
    "category": "資源物（金属類）"
  },
  {
    "name": "イヤホン",
    "category": "資源物（小型家電）"
  },
  {
    "name": "衣類",
    "category": "資源物（布・衣類）"
  },
  {
    "name": "衣類乾燥機",
    "category": "市では収集・処理しません"
  },
  {
    "name": "入れ歯",
    "category": "可燃ごみ"
  },
  {
    "name": "印鑑",
    "category": "可燃ごみ"
  },
  {
    "name": "インクカートリッジ（パソコン用）",
    "category": "可燃ごみ"
  },
  {
    "name": "インクリボン（ワープロ用含む）",
    "category": "可燃ごみ"
  },
  {
    "name": "印刷機（トナー含む）",
    "category": "資源物（小型家電）"
  },
  {
    "name": "飲料用紙パック（牛乳・ジュース）",
    "category": "資源物（紙類）"
  },
  {
    "name": "植木鉢（プラスチック製）",
    "category": "可燃ごみ"
  },
  {
    "name": "植木鉢（素焼き）",
    "category": "破砕ごみ"
  },
  {
    "name": "ウェットティッシュ",
    "category": "可燃ごみ"
  },
  {
    "name": "ウォータサーバー",
    "category": "市では収集しません"
  },
  {
    "name": "ウォータージャグ",
    "category": "破砕ごみ"
  },
  {
    "name": "浮き輪",
    "category": "可燃ごみ"
  },
  {
    "name": "うちわ",
    "category": "可燃ごみ"
  },
  {
    "name": "腕時計",
    "category": "資源物（小型家電）"
  },
  {
    "name": "乳母車",
    "category": "破砕ごみ"
  },
  {
    "name": "羽毛布団",
    "category": "破砕ごみ"
  },
  {
    "name": "エアークッション",
    "category": "可燃ごみ"
  },
  {
    "name": "エアコン（家庭用）",
    "category": "市では収集・処理しません"
  },
  {
    "name": "映写機",
    "category": "資源物（小型家電）"
  },
  {
    "name": "液晶テレビ",
    "category": "市では収集・処理しません"
  },
  {
    "name": "枝・葉類",
    "category": "可燃ごみ"
  },
  {
    "name": "枝きりばさみ",
    "category": "資源物（金属類）"
  },
  {
    "name": "絵の具のチューブ",
    "category": "可燃ごみ"
  },
  {
    "name": "絵の具のパレット",
    "category": "可燃ごみ"
  },
  {
    "name": "絵筆",
    "category": "可燃ごみ"
  },
  {
    "name": "絵本",
    "category": "資源物（紙類）"
  },
  {
    "name": "ＭＤ",
    "category": "可燃ごみ"
  },
  {
    "name": "ＭＤプレイヤー（携帯型）",
    "category": "資源物（小型家電）"
  },
  {
    "name": "ＭＰ３プレイヤー",
    "category": "資源物（小型家電）"
  },
  {
    "name": "LED電球",
    "category": "資源物（蛍光管）"
  },
  {
    "name": "ＬＰＧボンベ類",
    "category": "市では収集・処理しません"
  },
  {
    "name": "エレクトーン",
    "category": "市では収集しません"
  },
  {
    "name": "園芸用支柱",
    "category": "資源物（金属類）"
  },
  {
    "name": "エンジンオイル",
    "category": "市では収集・処理しません"
  },
  {
    "name": "延長コード",
    "category": "資源物（金属類）"
  },
  {
    "name": "鉛筆、鉛筆の削りかす",
    "category": "可燃ごみ"
  },
  {
    "name": "鉛筆削り器（手動）",
    "category": "可燃ごみ"
  },
  {
    "name": "鉛筆削り器（電動）",
    "category": "資源物（小型家電）"
  },
  {
    "name": "オーディオラック",
    "category": "粗大ごみ指定品目"
  },
  {
    "name": "オートバイ（原付自転車含む）",
    "category": "市では収集・処理しません"
  },
  {
    "name": "オートバイのバッテリー（原付自転車用を含む）",
    "category": "資源物（乾電池・水銀体温計）"
  },
  {
    "name": "オーブントースター",
    "category": "資源物（小型家電）"
  },
  {
    "name": "オーブンレンジ",
    "category": "資源物（小型家電）"
  },
  {
    "name": "オイルヒーター",
    "category": "資源物（小型家電）"
  },
  {
    "name": "王冠",
    "category": "資源物（金属類）"
  },
  {
    "name": "桶",
    "category": "可燃ごみ"
  },
  {
    "name": "おしりふき",
    "category": "可燃ごみ"
  },
  {
    "name": "お玉（金属製）",
    "category": "資源物（金属類）"
  },
  {
    "name": "お茶の缶",
    "category": "資源物（金属類）"
  },
  {
    "name": "おねしょシーツ（ペット用含む）",
    "category": "可燃ごみ"
  },
  {
    "name": "斧【おの】",
    "category": "資源物（金属類）"
  },
  {
    "name": "折り畳みベット",
    "category": "粗大ごみ指定品目"
  },
  {
    "name": "おまる（プラスチック製）",
    "category": "破砕ごみ"
  },
  {
    "name": "おむつ",
    "category": "可燃ごみ"
  },
  {
    "name": "おむつカバー",
    "category": "可燃ごみ"
  },
  {
    "name": "おもちゃ（プラスチック製）",
    "category": "可燃ごみ"
  },
  {
    "name": "おもり（釣具）",
    "category": "資源物（金属類）"
  },
  {
    "name": "オルガン",
    "category": "市では収集しません"
  },
  {
    "name": "おろしがね（金属製）",
    "category": "資源物（金属類）"
  },
  {
    "name": "音楽プレーヤー（携帯型）",
    "category": "資源物（小型家電）"
  },
  {
    "name": "温度計",
    "category": "破砕ごみ"
  },
  {
    "name": "温風器",
    "category": "資源物（小型家電）"
  },
  {
    "name": "ガーゼ",
    "category": "可燃ごみ"
  },
  {
    "name": "カーテン（レース含む）",
    "category": "資源物（布・衣類）"
  },
  {
    "name": "カーテンレール",
    "category": "資源物（金属類）"
  },
  {
    "name": "カーペット",
    "category": "破砕ごみ"
  },
  {
    "name": "カーボン紙",
    "category": "可燃ごみ"
  },
  {
    "name": "カーボンヒーター",
    "category": "資源物（小型家電）"
  },
  {
    "name": "貝殻",
    "category": "可燃ごみ"
  },
  {
    "name": "懐中電灯",
    "category": "資源物（小型家電）"
  },
  {
    "name": "買い物袋",
    "category": "可燃ごみ"
  },
  {
    "name": "カイロ（使い捨て）",
    "category": "可燃ごみ"
  },
  {
    "name": "鏡",
    "category": "破砕ごみ"
  },
  {
    "name": "鍵",
    "category": "資源物（金属類）"
  },
  {
    "name": "額縁（木製）",
    "category": "可燃ごみ"
  },
  {
    "name": "傘",
    "category": "破砕ごみ"
  },
  {
    "name": "加湿器",
    "category": "資源物（小型家電）"
  },
  {
    "name": "菓子の缶",
    "category": "資源物（金属類）"
  },
  {
    "name": "菓子箱",
    "category": "資源物（紙類）"
  },
  {
    "name": "菓子袋（ビニール加工製）",
    "category": "可燃ごみ"
  },
  {
    "name": "ガス炊飯器",
    "category": "資源物（金属類）"
  },
  {
    "name": "ガスストーブ",
    "category": "資源物（金属類）"
  },
  {
    "name": "ガステーブル（ガスコンロ）",
    "category": "資源物（金属類）"
  },
  {
    "name": "ガスレンジ",
    "category": "資源物（金属類）"
  },
  {
    "name": "ガスファンヒーター",
    "category": "資源物（小型家電）"
  },
  {
    "name": "ガスマット（レンジカバー）",
    "category": "資源物（金属類）"
  },
  {
    "name": "カセットテープ",
    "category": "可燃ごみ"
  },
  {
    "name": "カセットデッキ",
    "category": "資源物（小型家電）"
  },
  {
    "name": "カセットフィルム",
    "category": "可燃ごみ"
  },
  {
    "name": "カセットボンベ（卓上用）",
    "category": "資源物（スプレー缶）"
  },
  {
    "name": "カタログ",
    "category": "資源物（紙類）"
  },
  {
    "name": "カッターナイフ",
    "category": "資源物（金属類）"
  },
  {
    "name": "カッターの刃",
    "category": "資源物（金属類）"
  },
  {
    "name": "カット綿",
    "category": "可燃ごみ"
  },
  {
    "name": "合羽【かっぱ】",
    "category": "可燃ごみ"
  },
  {
    "name": "カップラーメン容器、上ぶた",
    "category": "可燃ごみ"
  },
  {
    "name": "かつら",
    "category": "可燃ごみ"
  },
  {
    "name": "蚊取りマット",
    "category": "資源物（小型家電）"
  },
  {
    "name": "金網",
    "category": "資源物（金属類）"
  },
  {
    "name": "かなづち",
    "category": "資源物（金属類）"
  },
  {
    "name": "かばん",
    "category": "可燃ごみ"
  },
  {
    "name": "画板（木製）",
    "category": "可燃ごみ"
  },
  {
    "name": "画鋲",
    "category": "資源物（金属類）"
  },
  {
    "name": "花瓶（ガラス製、陶磁器製）",
    "category": "破砕ごみ"
  },
  {
    "name": "鎌【かま】",
    "category": "資源物（金属類）"
  },
  {
    "name": "紙くず",
    "category": "可燃ごみ"
  },
  {
    "name": "紙コップ・紙皿",
    "category": "可燃ごみ"
  },
  {
    "name": "かみそり（金属製）",
    "category": "資源物（金属類）"
  },
  {
    "name": "紙粘土",
    "category": "可燃ごみ"
  },
  {
    "name": "髪の毛",
    "category": "可燃ごみ"
  },
  {
    "name": "紙パック（掃除機用）",
    "category": "可燃ごみ"
  },
  {
    "name": "紙ひも",
    "category": "可燃ごみ"
  },
  {
    "name": "紙袋",
    "category": "資源物（紙類）"
  },
  {
    "name": "ガムテープ（紙・布製）",
    "category": "可燃ごみ"
  },
  {
    "name": "カメラ",
    "category": "資源物（小型家電）"
  },
  {
    "name": "カメラのフィルム",
    "category": "可燃ごみ"
  },
  {
    "name": "蚊帳（麻・木綿製）",
    "category": "可燃ごみ"
  },
  {
    "name": "画用紙",
    "category": "資源物（紙類）"
  },
  {
    "name": "カラーボックス（木製）",
    "category": "破砕ごみ"
  },
  {
    "name": "ガラス食器",
    "category": "破砕ごみ"
  },
  {
    "name": "ガラス調度品",
    "category": "破砕ごみ"
  },
  {
    "name": "ガラス戸（木枠）",
    "category": "破砕ごみ"
  },
  {
    "name": "ガラスの破片",
    "category": "破砕ごみ"
  },
  {
    "name": "カレンダー",
    "category": "資源物（紙類）"
  },
  {
    "name": "カレンダーのとじ部分（金属製）",
    "category": "資源物（金属類）"
  },
  {
    "name": "革靴",
    "category": "可燃ごみ"
  },
  {
    "name": "革ジャンパー",
    "category": "資源物（布・衣類）"
  },
  {
    "name": "革製品（衣類以外）",
    "category": "可燃ごみ"
  },
  {
    "name": "缶（飲料缶）",
    "category": "資源物（飲料缶）"
  },
  {
    "name": "缶（飲料缶以外）",
    "category": "資源物（金属類）"
  },
  {
    "name": "缶（スプレー缶）",
    "category": "資源物（スプレー缶）"
  },
  {
    "name": "缶（一斗缶）",
    "category": "資源物（金属類）"
  },
  {
    "name": "換気扇",
    "category": "資源物（小型家電）"
  },
  {
    "name": "缶切、缶切器（金属製）",
    "category": "資源物（金属類）"
  },
  {
    "name": "感光紙（青焼）",
    "category": "可燃ごみ"
  },
  {
    "name": "乾燥剤",
    "category": "可燃ごみ"
  },
  {
    "name": "乾電池",
    "category": "資源物（乾電池・水銀体温計）"
  },
  {
    "name": "感熱紙",
    "category": "可燃ごみ"
  },
  {
    "name": "キーボード（楽器）",
    "category": "資源物（小型家電）"
  },
  {
    "name": "キーボード（パソコンの入力機器）",
    "category": "資源物（小型家電）"
  },
  {
    "name": "木くず",
    "category": "可燃ごみ"
  },
  {
    "name": "ギター",
    "category": "破砕ごみ"
  },
  {
    "name": "木槌【きづち】",
    "category": "可燃ごみ"
  },
  {
    "name": "キッチンマット",
    "category": "可燃ごみ"
  },
  {
    "name": "着物・着物の帯",
    "category": "資源物（布・衣類）"
  },
  {
    "name": "脚立（金属製）",
    "category": "資源物（金属類）"
  },
  {
    "name": "キャビネット（金属製）",
    "category": "資源物（金属類）"
  },
  {
    "name": "キャンプ用テーブル（アルミ製）",
    "category": "資源物（金属類）"
  },
  {
    "name": "急須（陶磁器製）",
    "category": "破砕ごみ"
  },
  {
    "name": "牛乳パック",
    "category": "資源物（紙類）"
  },
  {
    "name": "牛乳びん",
    "category": "資源物（びん）"
  },
  {
    "name": "吸盤",
    "category": "可燃ごみ"
  },
  {
    "name": "強化ガラス",
    "category": "破砕ごみ"
  },
  {
    "name": "鏡台（ドレッサー）",
    "category": "粗大ごみ指定品目"
  },
  {
    "name": "きり",
    "category": "資源物（金属類）"
  },
  {
    "name": "金魚鉢",
    "category": "破砕ごみ"
  },
  {
    "name": "金庫",
    "category": "市では収集しません"
  },
  {
    "name": "金属キャップ（ふた）",
    "category": "資源物（金属類）"
  },
  {
    "name": "クーハン（籐製）",
    "category": "可燃ごみ"
  },
  {
    "name": "クーラー（エアコン）",
    "category": "市では収集・処理しません"
  },
  {
    "name": "クーラーボックス",
    "category": "破砕ごみ"
  },
  {
    "name": "空気入れ（金属製）",
    "category": "資源物（金属類）"
  },
  {
    "name": "空気清浄機",
    "category": "資源物（小型家電）"
  },
  {
    "name": "釘",
    "category": "資源物（金属類）"
  },
  {
    "name": "草・花",
    "category": "可燃ごみ"
  },
  {
    "name": "草刈り機（家庭用）",
    "category": "資源物（金属類）"
  },
  {
    "name": "鎖（金属製）",
    "category": "資源物（金属類）"
  },
  {
    "name": "櫛（木・竹製）",
    "category": "可燃ごみ"
  },
  {
    "name": "串（木・竹製）",
    "category": "可燃ごみ"
  },
  {
    "name": "薬（液体のものを除く）",
    "category": "可燃ごみ"
  },
  {
    "name": "くだもの、くだものの皮",
    "category": "可燃ごみ"
  },
  {
    "name": "果物などを入れたネット",
    "category": "可燃ごみ"
  },
  {
    "name": "口紅のケース",
    "category": "可燃ごみ"
  },
  {
    "name": "靴",
    "category": "可燃ごみ"
  },
  {
    "name": "クッキングペーパー",
    "category": "可燃ごみ"
  },
  {
    "name": "くつ下",
    "category": "資源物（布・衣類）"
  },
  {
    "name": "クッション",
    "category": "可燃ごみ"
  },
  {
    "name": "首輪",
    "category": "可燃ごみ"
  },
  {
    "name": "クリーニング仕上げ袋",
    "category": "可燃ごみ"
  },
  {
    "name": "クリスマスツリー",
    "category": "可燃ごみ"
  },
  {
    "name": "クリスマスツリーの装飾品",
    "category": "資源物（金属類）"
  },
  {
    "name": "クリップ（金属製）",
    "category": "資源物（金属類）"
  },
  {
    "name": "車椅子",
    "category": "資源物（金属類）"
  },
  {
    "name": "クレヨン",
    "category": "可燃ごみ"
  },
  {
    "name": "グローブ（革製）",
    "category": "可燃ごみ"
  },
  {
    "name": "グローランプ",
    "category": "資源物（蛍光管）"
  },
  {
    "name": "鍬【くわ】",
    "category": "資源物（金属類）"
  },
  {
    "name": "軍手（布製）",
    "category": "可燃ごみ"
  },
  {
    "name": "ゲーム機",
    "category": "資源物（小型家電）"
  },
  {
    "name": "ゲームソフト",
    "category": "可燃ごみ"
  },
  {
    "name": "蛍光管",
    "category": "資源物（蛍光管）"
  },
  {
    "name": "珪藻土バスマット",
    "category": "破砕ごみ"
  },
  {
    "name": "携帯電話",
    "category": "資源物（小型家電）"
  },
  {
    "name": "毛糸",
    "category": "可燃ごみ"
  },
  {
    "name": "消しゴム",
    "category": "可燃ごみ"
  },
  {
    "name": "化粧品の容器（金属製）",
    "category": "資源物（金属類）"
  },
  {
    "name": "化粧品のびん",
    "category": "破砕ごみ"
  },
  {
    "name": "下駄",
    "category": "可燃ごみ"
  },
  {
    "name": "下駄箱",
    "category": "粗大ごみ指定品目"
  },
  {
    "name": "血圧計",
    "category": "資源物（小型家電）"
  },
  {
    "name": "玄関泥落としマット（金属製）",
    "category": "資源物（金属類）"
  },
  {
    "name": "玄関マット（化学繊維）",
    "category": "可燃ごみ"
  },
  {
    "name": "剣山",
    "category": "資源物（金属類）"
  },
  {
    "name": "原付自転車",
    "category": "市では収集・処理しません"
  },
  {
    "name": "顕微鏡",
    "category": "資源物（金属類）"
  },
  {
    "name": "ゴーグル",
    "category": "可燃ごみ"
  },
  {
    "name": "コーヒーメーカー",
    "category": "資源物（小型家電）"
  },
  {
    "name": "碁石",
    "category": "破砕ごみ"
  },
  {
    "name": "光学ドライブ",
    "category": "資源物（小型家電）"
  },
  {
    "name": "工具類（金属製）",
    "category": "資源物（金属類）"
  },
  {
    "name": "氷かき器",
    "category": "可燃ごみ"
  },
  {
    "name": "氷枕",
    "category": "可燃ごみ"
  },
  {
    "name": "黒板",
    "category": "破砕ごみ"
  },
  {
    "name": "ござ（室内用）",
    "category": "破砕ごみ"
  },
  {
    "name": "こたつ（ホームこたつ）",
    "category": "資源物（小型家電）"
  },
  {
    "name": "こたつ掛けぶとん",
    "category": "破砕ごみ"
  },
  {
    "name": "こたつ掛け毛布",
    "category": "資源物（布・衣類）"
  },
  {
    "name": "コップ（ガラス製）",
    "category": "破砕ごみ"
  },
  {
    "name": "粉薬の包装パック（ビニール加工紙）",
    "category": "可燃ごみ"
  },
  {
    "name": "ごみ箱（プラスチック製）",
    "category": "破砕ごみ"
  },
  {
    "name": "ゴム製品",
    "category": "可燃ごみ"
  },
  {
    "name": "米びつ（金属製）",
    "category": "資源物（金属類）"
  },
  {
    "name": "コルク",
    "category": "可燃ごみ"
  },
  {
    "name": "ゴルフクラブ",
    "category": "資源物（金属類）"
  },
  {
    "name": "ゴルフバッグ",
    "category": "破砕ごみ"
  },
  {
    "name": "コンクリート類",
    "category": "破砕ごみ"
  },
  {
    "name": "コンタクトレンズ",
    "category": "可燃ごみ"
  },
  {
    "name": "コンパクト",
    "category": "可燃ごみ"
  },
  {
    "name": "コンポスター",
    "category": "破砕ごみ"
  },
  {
    "name": "サーフボード",
    "category": "破砕ごみ"
  },
  {
    "name": "座椅子（家具調、ソファータイプを除く）",
    "category": "破砕ごみ"
  },
  {
    "name": "サイドボード",
    "category": "粗大ごみ指定品目"
  },
  {
    "name": "財布",
    "category": "可燃ごみ"
  },
  {
    "name": "サインペン",
    "category": "可燃ごみ"
  },
  {
    "name": "座卓",
    "category": "粗大ごみ指定品目"
  },
  {
    "name": "雑誌",
    "category": "資源物（紙類）"
  },
  {
    "name": "殺虫剤のスプレー缶",
    "category": "資源物（スプレー缶）"
  },
  {
    "name": "ざぶとん",
    "category": "可燃ごみ"
  },
  {
    "name": "皿（ガラス製、陶磁器製）",
    "category": "破砕ごみ"
  },
  {
    "name": "皿（プラスチック製、紙製、木製）",
    "category": "可燃ごみ"
  },
  {
    "name": "皿（金属製）",
    "category": "資源物（金属類）"
  },
  {
    "name": "ざる類（プラスチック製）",
    "category": "可燃ごみ"
  },
  {
    "name": "サングラス（プラスチック製）",
    "category": "可燃ごみ"
  },
  {
    "name": "サンダル",
    "category": "可燃ごみ"
  },
  {
    "name": "三輪車（金属製）",
    "category": "資源物（金属類）"
  },
  {
    "name": "シーツ",
    "category": "資源物（布・衣類）"
  },
  {
    "name": "ＣＤソフト（ケース含む）",
    "category": "可燃ごみ"
  },
  {
    "name": "ＣＤラジカセ",
    "category": "資源物（小型家電）"
  },
  {
    "name": "シート（ビニール製）",
    "category": "可燃ごみ"
  },
  {
    "name": "シール",
    "category": "可燃ごみ"
  },
  {
    "name": "地下たび",
    "category": "可燃ごみ"
  },
  {
    "name": "磁気カード",
    "category": "可燃ごみ"
  },
  {
    "name": "敷きパッド",
    "category": "破砕ごみ"
  },
  {
    "name": "磁気マット",
    "category": "破砕ごみ"
  },
  {
    "name": "磁気マットレス",
    "category": "破砕ごみ"
  },
  {
    "name": "磁石",
    "category": "可燃ごみ"
  },
  {
    "name": "辞書・辞典",
    "category": "資源物（紙類）"
  },
  {
    "name": "下着",
    "category": "資源物（布・衣類）"
  },
  {
    "name": "シップ薬",
    "category": "可燃ごみ"
  },
  {
    "name": "自転車（電動アシスト自転車含む）",
    "category": "資源物（金属類）"
  },
  {
    "name": "自動車用タイヤチェーン",
    "category": "資源物（金属類）"
  },
  {
    "name": "竹刀【しない】",
    "category": "破砕ごみ"
  },
  {
    "name": "シャープペンシル",
    "category": "可燃ごみ"
  },
  {
    "name": "写真",
    "category": "可燃ごみ"
  },
  {
    "name": "しゃもじ",
    "category": "可燃ごみ"
  },
  {
    "name": "ジャングルジム（プラスチック製）",
    "category": "破砕ごみ"
  },
  {
    "name": "シャンプーの容器",
    "category": "可燃ごみ"
  },
  {
    "name": "ジューサーミキサー",
    "category": "資源物（小型家電）"
  },
  {
    "name": "シュレッダー紙ごみ",
    "category": "可燃ごみ"
  },
  {
    "name": "じゅうたん",
    "category": "破砕ごみ"
  },
  {
    "name": "充電器",
    "category": "資源物（小型家電）"
  },
  {
    "name": "充電式電池",
    "category": "資源物（乾電池・水銀体温計）"
  },
  {
    "name": "収納ケース（プラスチック製）",
    "category": "破砕ごみ"
  },
  {
    "name": "１６mmフィルム",
    "category": "可燃ごみ"
  },
  {
    "name": "消火器",
    "category": "市では収集・処理しません"
  },
  {
    "name": "定規（木製）",
    "category": "可燃ごみ"
  },
  {
    "name": "将棋のこま",
    "category": "可燃ごみ"
  },
  {
    "name": "錠剤のシート（プラスチック製）",
    "category": "可燃ごみ"
  },
  {
    "name": "障子戸（木製）",
    "category": "破砕ごみ"
  },
  {
    "name": "消臭スプレー",
    "category": "資源物（スプレー缶）"
  },
  {
    "name": "浄水器",
    "category": "資源物（小型家電）"
  },
  {
    "name": "焼酎の容器（ペットボトル）",
    "category": "ペットボトル"
  },
  {
    "name": "照明器具",
    "category": "資源物（小型家電）"
  },
  {
    "name": "しょうゆの容器（ペットボトル）",
    "category": "ペットボトル"
  },
  {
    "name": "ジョウロ（プラスチック製）",
    "category": "可燃ごみ"
  },
  {
    "name": "食用油の容器（プラスチック製）",
    "category": "可燃ごみ"
  },
  {
    "name": "除湿機",
    "category": "資源物（小型家電）"
  },
  {
    "name": "除湿剤",
    "category": "可燃ごみ"
  },
  {
    "name": "書籍",
    "category": "資源物（紙類）"
  },
  {
    "name": "食器（プラスチック製）",
    "category": "可燃ごみ"
  },
  {
    "name": "食器（陶磁器・ガラス製）",
    "category": "破砕ごみ"
  },
  {
    "name": "食器乾燥機",
    "category": "資源物（小型家電）"
  },
  {
    "name": "食器洗浄機",
    "category": "資源物（小型家電）"
  },
  {
    "name": "食器棚",
    "category": "粗大ごみ指定品目"
  },
  {
    "name": "食品トレイ（白色）",
    "category": "可燃ごみ"
  },
  {
    "name": "食品トレイ（色柄）",
    "category": "可燃ごみ"
  },
  {
    "name": "シルバーカー",
    "category": "破砕ごみ"
  },
  {
    "name": "新聞紙",
    "category": "資源物（紙類）"
  },
  {
    "name": "スーツケース",
    "category": "破砕ごみ"
  },
  {
    "name": "水槽",
    "category": "破砕ごみ"
  },
  {
    "name": "水筒（金属製）",
    "category": "資源物（金属類）"
  },
  {
    "name": "炊飯器",
    "category": "資源物（小型家電）"
  },
  {
    "name": "スカーフ",
    "category": "資源物（布・衣類）"
  },
  {
    "name": "スキー板、スキー靴",
    "category": "破砕ごみ"
  },
  {
    "name": "スキーウェア",
    "category": "資源物（布・衣類）"
  },
  {
    "name": "スキーストック（金属製）",
    "category": "資源物（金属類）"
  },
  {
    "name": "スキー手袋",
    "category": "資源物（布・衣類）"
  },
  {
    "name": "スケートボード",
    "category": "破砕ごみ"
  },
  {
    "name": "スコップ（金属製）",
    "category": "資源物（金属類）"
  },
  {
    "name": "すずり",
    "category": "破砕ごみ"
  },
  {
    "name": "すだれ（木・竹製）",
    "category": "破砕ごみ"
  },
  {
    "name": "スタンプ台（金属製）",
    "category": "資源物（金属類）"
  },
  {
    "name": "ステレオ",
    "category": "資源物（小型家電）"
  },
  {
    "name": "ストーブ",
    "category": "資源物（金属類）"
  },
  {
    "name": "ストッキング",
    "category": "資源物（布・衣類）"
  },
  {
    "name": "ストラップ",
    "category": "可燃ごみ"
  },
  {
    "name": "スニーカー",
    "category": "可燃ごみ"
  },
  {
    "name": "スノーボード",
    "category": "破砕ごみ"
  },
  {
    "name": "すのこ",
    "category": "可燃ごみ"
  },
  {
    "name": "スパナ",
    "category": "資源物（金属類）"
  },
  {
    "name": "スピーカー",
    "category": "資源物（小型家電）"
  },
  {
    "name": "スプーン（金属製）",
    "category": "資源物（金属類）"
  },
  {
    "name": "スプリングマットレス",
    "category": "粗大ごみ指定品目"
  },
  {
    "name": "スプレー缶",
    "category": "資源物（スプレー缶）"
  },
  {
    "name": "すべり台（幼児用）",
    "category": "破砕ごみ"
  },
  {
    "name": "スポンジ",
    "category": "可燃ごみ"
  },
  {
    "name": "スマートフォン",
    "category": "資源物（小型家電）"
  },
  {
    "name": "炭",
    "category": "可燃ごみ"
  },
  {
    "name": "墨",
    "category": "可燃ごみ"
  },
  {
    "name": "すりガラス",
    "category": "破砕ごみ"
  },
  {
    "name": "すり鉢",
    "category": "破砕ごみ"
  },
  {
    "name": "スリッパ",
    "category": "可燃ごみ"
  },
  {
    "name": "セーター",
    "category": "資源物（布・衣類）"
  },
  {
    "name": "生理用品",
    "category": "可燃ごみ"
  },
  {
    "name": "石油ストーブ",
    "category": "資源物（金属類）"
  },
  {
    "name": "石油ポンプ",
    "category": "可燃ごみ"
  },
  {
    "name": "せっけん",
    "category": "可燃ごみ"
  },
  {
    "name": "接着剤",
    "category": "可燃ごみ"
  },
  {
    "name": "せともの",
    "category": "破砕ごみ"
  },
  {
    "name": "背広",
    "category": "資源物（布・衣類）"
  },
  {
    "name": "セラミックファンヒーター",
    "category": "資源物（小型家電）"
  },
  {
    "name": "セロハンテープ",
    "category": "可燃ごみ"
  },
  {
    "name": "扇子（木製）",
    "category": "可燃ごみ"
  },
  {
    "name": "洗濯機",
    "category": "市では収集・処理しません"
  },
  {
    "name": "洗濯バサミ（プラスチック製）",
    "category": "可燃ごみ"
  },
  {
    "name": "剪定した庭木",
    "category": "可燃ごみ"
  },
  {
    "name": "栓抜き（金属製）",
    "category": "資源物（金属類）"
  },
  {
    "name": "扇風機",
    "category": "資源物（小型家電）"
  },
  {
    "name": "千枚とおし",
    "category": "資源物（金属類）"
  },
  {
    "name": "洗剤の上ぶた（プラスチック製）",
    "category": "可燃ごみ"
  },
  {
    "name": "洗剤のスプーン（プラスチック製）",
    "category": "可燃ごみ"
  },
  {
    "name": "洗剤の箱",
    "category": "可燃ごみ"
  },
  {
    "name": "センサーライト",
    "category": "資源物（小型家電）"
  },
  {
    "name": "洗面器（プラスチック製）",
    "category": "可燃ごみ"
  },
  {
    "name": "ソースの容器（プラスチック製）",
    "category": "可燃ごみ"
  },
  {
    "name": "造花",
    "category": "可燃ごみ"
  },
  {
    "name": "双眼鏡",
    "category": "可燃ごみ"
  },
  {
    "name": "ぞうきん",
    "category": "可燃ごみ"
  },
  {
    "name": "掃除機",
    "category": "資源物（小型家電）"
  },
  {
    "name": "掃除機の紙パック、掃除機のごみ",
    "category": "可燃ごみ"
  },
  {
    "name": "ぞうり（革製、ビニール製）",
    "category": "可燃ごみ"
  },
  {
    "name": "ソファー",
    "category": "粗大ごみ指定品目"
  },
  {
    "name": "そり（子供用玩具）（プラスチック製）",
    "category": "破砕ごみ"
  },
  {
    "name": "そろばん（木製）",
    "category": "可燃ごみ"
  },
  {
    "name": "体温計（電子）",
    "category": "資源物（小型家電）"
  },
  {
    "name": "体重計",
    "category": "資源物（小型家電）"
  },
  {
    "name": "タイヤ",
    "category": "市では収集・処理しません"
  },
  {
    "name": "タイヤチェーン",
    "category": "資源物（金属類）"
  },
  {
    "name": "タイヤホイール",
    "category": "資源物（金属類）"
  },
  {
    "name": "タイル",
    "category": "破砕ごみ"
  },
  {
    "name": "タオル（汚れの少ないもの）",
    "category": "資源物（布・衣類）"
  },
  {
    "name": "タオルケット",
    "category": "資源物（布・衣類）"
  },
  {
    "name": "畳",
    "category": "破砕ごみ"
  },
  {
    "name": "脱脂綿",
    "category": "可燃ごみ"
  },
  {
    "name": "脱臭剤",
    "category": "可燃ごみ"
  },
  {
    "name": "タッパー",
    "category": "可燃ごみ"
  },
  {
    "name": "タバコの銀紙、箱、吸殻（フィルター含む）",
    "category": "可燃ごみ"
  },
  {
    "name": "タブレットPC",
    "category": "資源物（小型家電）"
  },
  {
    "name": "卵のから",
    "category": "可燃ごみ"
  },
  {
    "name": "卵のパック",
    "category": "可燃ごみ"
  },
  {
    "name": "たわし類",
    "category": "可燃ごみ"
  },
  {
    "name": "炭酸ガスシリンダー（ボンベ）",
    "category": "市では収集・処理しません"
  },
  {
    "name": "たんす",
    "category": "粗大ごみ指定品目"
  },
  {
    "name": "ダンベル（金属製）",
    "category": "資源物（金属類）"
  },
  {
    "name": "ダンボール",
    "category": "資源物（紙類）"
  },
  {
    "name": "地球儀",
    "category": "破砕ごみ"
  },
  {
    "name": "チャイルドシート",
    "category": "破砕ごみ"
  },
  {
    "name": "茶がら",
    "category": "可燃ごみ"
  },
  {
    "name": "茶碗",
    "category": "破砕ごみ"
  },
  {
    "name": "注射針、注射器（在宅治療用）",
    "category": "市では収集・処理しません"
  },
  {
    "name": "調味料びん",
    "category": "資源物（びん）"
  },
  {
    "name": "調味料の容器（プラスチック製）",
    "category": "可燃ごみ"
  },
  {
    "name": "チョーク",
    "category": "可燃ごみ"
  },
  {
    "name": "チラシ（広告）",
    "category": "資源物（紙類）"
  },
  {
    "name": "ちり紙",
    "category": "可燃ごみ"
  },
  {
    "name": "ちりとり（プラスチック製）",
    "category": "可燃ごみ"
  },
  {
    "name": "机",
    "category": "粗大ごみ指定品目"
  },
  {
    "name": "土",
    "category": "破砕ごみ"
  },
  {
    "name": "つっぱり棒",
    "category": "資源物（金属類）"
  },
  {
    "name": "壷（陶磁器製）",
    "category": "破砕ごみ"
  },
  {
    "name": "つまようじ",
    "category": "可燃ごみ"
  },
  {
    "name": "積木",
    "category": "可燃ごみ"
  },
  {
    "name": "つめ切り（金属製）",
    "category": "資源物（金属類）"
  },
  {
    "name": "釣り糸",
    "category": "可燃ごみ"
  },
  {
    "name": "釣竿",
    "category": "破砕ごみ"
  },
  {
    "name": "釣りリール（金属製）",
    "category": "資源物（金属類）"
  },
  {
    "name": "テープ（ビニール製）",
    "category": "可燃ごみ"
  },
  {
    "name": "テープカッター",
    "category": "可燃ごみ"
  },
  {
    "name": "テーブル",
    "category": "粗大ごみ指定品目"
  },
  {
    "name": "テーブルクロス（布製）",
    "category": "資源物（布・衣類）"
  },
  {
    "name": "ディスプレイ（パソコン用）",
    "category": "資源物（小型家電）"
  },
  {
    "name": "ティッシュペーパー",
    "category": "可燃ごみ"
  },
  {
    "name": "ティッシュの外箱",
    "category": "資源物（紙類）"
  },
  {
    "name": "ＤＶＤソフト（ケース含む）",
    "category": "可燃ごみ"
  },
  {
    "name": "ＤＶＤレコーダー（プレーヤー）",
    "category": "資源物（小型家電）"
  },
  {
    "name": "手提げ金庫",
    "category": "資源物（金属類）"
  },
  {
    "name": "デジタルオーディオプレーヤー",
    "category": "資源物（小型家電）"
  },
  {
    "name": "デスクマット",
    "category": "可燃ごみ"
  },
  {
    "name": "鉄アレイ",
    "category": "資源物（金属類）"
  },
  {
    "name": "テニスラケット",
    "category": "破砕ごみ"
  },
  {
    "name": "手袋",
    "category": "資源物（布・衣類）"
  },
  {
    "name": "テレビ",
    "category": "市では収集・処理しません"
  },
  {
    "name": "テレビゲーム本体",
    "category": "資源物（小型家電）"
  },
  {
    "name": "テレビ台",
    "category": "粗大ごみ指定品目"
  },
  {
    "name": "テレフォンカード",
    "category": "可燃ごみ"
  },
  {
    "name": "電気あんか",
    "category": "資源物（小型家電）"
  },
  {
    "name": "電気カーペット",
    "category": "資源物（小型家電）"
  },
  {
    "name": "電気工具（金属製）",
    "category": "資源物（小型家電）"
  },
  {
    "name": "電気ストーブ",
    "category": "資源物（小型家電）"
  },
  {
    "name": "電気髭剃り",
    "category": "資源物（小型家電）"
  },
  {
    "name": "電気ポット",
    "category": "資源物（小型家電）"
  },
  {
    "name": "電気毛布",
    "category": "資源物（小型家電）"
  },
  {
    "name": "電球（LEDを含む）",
    "category": "資源物（蛍光管）"
  },
  {
    "name": "電子辞書",
    "category": "資源物（小型家電）"
  },
  {
    "name": "電子たばこ",
    "category": "資源物（小型家電）"
  },
  {
    "name": "電子レンジ",
    "category": "資源物（小型家電）"
  },
  {
    "name": "電線・電気コード",
    "category": "資源物（金属類）"
  },
  {
    "name": "天体望遠鏡",
    "category": "資源物（金属類）"
  },
  {
    "name": "電卓",
    "category": "資源物（小型家電）"
  },
  {
    "name": "点滴パック及びチューブ類（在宅治療用）",
    "category": "可燃ごみ"
  },
  {
    "name": "テント（家庭用）",
    "category": "破砕ごみ"
  },
  {
    "name": "電動歯ブラシ",
    "category": "資源物（小型家電）"
  },
  {
    "name": "電動マッサージ機（いす式）",
    "category": "粗大ごみ指定品目"
  },
  {
    "name": "てんぷらガード",
    "category": "資源物（金属類）"
  },
  {
    "name": "てんぷら油",
    "category": "可燃ごみ"
  },
  {
    "name": "電話機",
    "category": "資源物（小型家電）"
  },
  {
    "name": "電話帳",
    "category": "資源物（紙類）"
  },
  {
    "name": "トースター",
    "category": "資源物（小型家電）"
  },
  {
    "name": "砥石【といし】",
    "category": "破砕ごみ"
  },
  {
    "name": "陶磁器類",
    "category": "破砕ごみ"
  },
  {
    "name": "籐製品",
    "category": "可燃ごみ"
  },
  {
    "name": "透析パック及びチューブ類（在宅治療用）",
    "category": "可燃ごみ"
  },
  {
    "name": "とうふパック",
    "category": "可燃ごみ"
  },
  {
    "name": "時計",
    "category": "資源物（小型家電）"
  },
  {
    "name": "戸棚",
    "category": "粗大ごみ指定品目"
  },
  {
    "name": "トタン（金属製）",
    "category": "資源物（金属類）"
  },
  {
    "name": "トタン（プラスチック製）",
    "category": "破砕ごみ"
  },
  {
    "name": "土鍋",
    "category": "破砕ごみ"
  },
  {
    "name": "ドライバー（家庭用）",
    "category": "資源物（金属類）"
  },
  {
    "name": "ドライヤー",
    "category": "資源物（小型家電）"
  },
  {
    "name": "塗料",
    "category": "市では収集・処理しません"
  },
  {
    "name": "塗料容器（缶）",
    "category": "資源物（金属類）"
  },
  {
    "name": "トレイ類（プラスチック製）",
    "category": "可燃ごみ"
  },
  {
    "name": "ドレッサー（鏡台）",
    "category": "粗大ごみ指定品目"
  },
  {
    "name": "トロフィー",
    "category": "可燃ごみ"
  },
  {
    "name": "とんかち（金属製）",
    "category": "資源物（金属類）"
  },
  {
    "name": "ナイフ",
    "category": "資源物（金属類）"
  },
  {
    "name": "長靴",
    "category": "可燃ごみ"
  },
  {
    "name": "納豆の容器",
    "category": "可燃ごみ"
  },
  {
    "name": "鍋（金属製、ホーロー製）",
    "category": "資源物（金属類）"
  },
  {
    "name": "鍋焼きうどんのアルミ鍋",
    "category": "資源物（金属類）"
  },
  {
    "name": "生ごみ",
    "category": "可燃ごみ"
  },
  {
    "name": "生ごみ処理機",
    "category": "資源物（小型家電）"
  },
  {
    "name": "なわとび",
    "category": "可燃ごみ"
  },
  {
    "name": "ニカド電池",
    "category": "資源物（乾電池・水銀体温計）"
  },
  {
    "name": "二次電池",
    "category": "資源物（乾電池・水銀体温計）"
  },
  {
    "name": "人形（雛、五月人形含む）",
    "category": "可燃ごみ"
  },
  {
    "name": "人形ケース（ガラス製）",
    "category": "破砕ごみ"
  },
  {
    "name": "ぬいぐるみ",
    "category": "可燃ごみ"
  },
  {
    "name": "布くず",
    "category": "可燃ごみ"
  },
  {
    "name": "布類",
    "category": "資源物（布・衣類）"
  },
  {
    "name": "ネクタイ",
    "category": "資源物（布・衣類）"
  },
  {
    "name": "ネコ砂（砂以外）",
    "category": "可燃ごみ"
  },
  {
    "name": "ネジ",
    "category": "資源物（金属類）"
  },
  {
    "name": "寝袋",
    "category": "破砕ごみ"
  },
  {
    "name": "粘着カーペットクリーナー（シート紙）",
    "category": "可燃ごみ"
  },
  {
    "name": "粘土",
    "category": "可燃ごみ"
  },
  {
    "name": "ノート",
    "category": "資源物（紙類）"
  },
  {
    "name": "ノートパソコン",
    "category": "資源物（小型家電）"
  },
  {
    "name": "農業用ビニール",
    "category": "市では収集・処理しません"
  },
  {
    "name": "農薬",
    "category": "市では収集・処理しません"
  },
  {
    "name": "農薬びん",
    "category": "資源物（びん）"
  },
  {
    "name": "のこぎり",
    "category": "資源物（金属類）"
  },
  {
    "name": "のれん",
    "category": "可燃ごみ"
  },
  {
    "name": "ハードディスク",
    "category": "資源物（小型家電）"
  },
  {
    "name": "バーベキューセット（金属製）",
    "category": "資源物（金属類）"
  },
  {
    "name": "バーベル（金属製）",
    "category": "資源物（金属類）"
  },
  {
    "name": "ハーモニカ",
    "category": "資源物（金属類）"
  },
  {
    "name": "灰",
    "category": "可燃ごみ"
  },
  {
    "name": "灰皿（陶器製・ガラス製）",
    "category": "破砕ごみ"
  },
  {
    "name": "パイプ椅子（いす）",
    "category": "資源物（金属類）"
  },
  {
    "name": "パイプ管（ビニール製）",
    "category": "破砕ごみ"
  },
  {
    "name": "パイプベッド",
    "category": "粗大ごみ指定品目"
  },
  {
    "name": "廃油（灯油・ガソリン・オイル類）",
    "category": "市では収集・処理しません"
  },
  {
    "name": "バインダー（プラスチック製）",
    "category": "可燃ごみ"
  },
  {
    "name": "はがき",
    "category": "資源物（紙類）"
  },
  {
    "name": "はかり（金属製）",
    "category": "資源物（金属類）"
  },
  {
    "name": "ハケ（木製）",
    "category": "可燃ごみ"
  },
  {
    "name": "バケツ（プラスチック製）",
    "category": "破砕ごみ"
  },
  {
    "name": "箱類（木・プラスチック製）",
    "category": "可燃ごみ"
  },
  {
    "name": "ハサミ（金属製）",
    "category": "資源物（金属類）"
  },
  {
    "name": "箸",
    "category": "可燃ごみ"
  },
  {
    "name": "はしご（金属製）",
    "category": "資源物（金属類）"
  },
  {
    "name": "はしご（木製）",
    "category": "破砕ごみ"
  },
  {
    "name": "バスマット",
    "category": "破砕ごみ"
  },
  {
    "name": "パソコン（家庭用）",
    "category": "資源物（小型家電）"
  },
  {
    "name": "パソコンのパーツ",
    "category": "資源物（小型家電）"
  },
  {
    "name": "パソコンのプリンタ",
    "category": "資源物（小型家電）"
  },
  {
    "name": "パソコンのディスプレイ",
    "category": "資源物（小型家電）"
  },
  {
    "name": "バッテリー（車、オートバイ、原付自転車、アシスト自転車用）",
    "category": "資源物（金属類）"
  },
  {
    "name": "バット（金属製）",
    "category": "資源物（金属類）"
  },
  {
    "name": "発泡スチロール",
    "category": "可燃ごみ"
  },
  {
    "name": "花火",
    "category": "可燃ごみ"
  },
  {
    "name": "パフ（化粧品）",
    "category": "可燃ごみ"
  },
  {
    "name": "歯ブラシ",
    "category": "可燃ごみ"
  },
  {
    "name": "歯磨きチューブ",
    "category": "可燃ごみ"
  },
  {
    "name": "刃物",
    "category": "資源物（金属類）"
  },
  {
    "name": "針",
    "category": "資源物（金属類）"
  },
  {
    "name": "針金",
    "category": "資源物（金属類）"
  },
  {
    "name": "ハロゲンヒーター",
    "category": "資源物（小型家電）"
  },
  {
    "name": "ハンガー（針金）",
    "category": "資源物（金属類）"
  },
  {
    "name": "ハンカチ",
    "category": "資源物（布・衣類）"
  },
  {
    "name": "はんこ",
    "category": "可燃ごみ"
  },
  {
    "name": "半紙",
    "category": "資源物（紙類）"
  },
  {
    "name": "パンスト",
    "category": "資源物（布・衣類）"
  },
  {
    "name": "絆創膏【ばんそうこう】",
    "category": "可燃ごみ"
  },
  {
    "name": "パンツ（下着）",
    "category": "資源物（布・衣類）"
  },
  {
    "name": "半纏【はんてん】",
    "category": "資源物（布・衣類）"
  },
  {
    "name": "ハンドバック",
    "category": "可燃ごみ"
  },
  {
    "name": "ハンマー（金属製）",
    "category": "資源物（金属類）"
  },
  {
    "name": "ビーチパラソル（金属製）",
    "category": "破砕ごみ"
  },
  {
    "name": "ビート板",
    "category": "可燃ごみ"
  },
  {
    "name": "ビールびん",
    "category": "資源物（びん）"
  },
  {
    "name": "ピアニカ",
    "category": "可燃ごみ"
  },
  {
    "name": "ピアノ",
    "category": "市では収集しません"
  },
  {
    "name": "美顔器",
    "category": "資源物（小型家電）"
  },
  {
    "name": "ひげそり（金属製）",
    "category": "資源物（金属類）"
  },
  {
    "name": "ビデオカメラ",
    "category": "資源物（小型家電）"
  },
  {
    "name": "ビデオテープ",
    "category": "可燃ごみ"
  },
  {
    "name": "ビデオデッキ",
    "category": "資源物（小型家電）"
  },
  {
    "name": "ビニールテープ",
    "category": "可燃ごみ"
  },
  {
    "name": "ビニール袋",
    "category": "可燃ごみ"
  },
  {
    "name": "避妊具",
    "category": "可燃ごみ"
  },
  {
    "name": "ひも（ビニール製）",
    "category": "可燃ごみ"
  },
  {
    "name": "びん（化粧品用を除く）",
    "category": "資源物（びん）"
  },
  {
    "name": "びん（化粧品用）",
    "category": "破砕ごみ"
  },
  {
    "name": "便せん",
    "category": "資源物（紙類）"
  },
  {
    "name": "ファイル（紙製）",
    "category": "資源物（紙類）"
  },
  {
    "name": "ファイル（プラスチック製）",
    "category": "可燃ごみ"
  },
  {
    "name": "ファックス付き電話",
    "category": "資源物（小型家電）"
  },
  {
    "name": "ファンヒーター",
    "category": "資源物（小型家電）"
  },
  {
    "name": "フィルム（ネガ）、フィルムケース",
    "category": "可燃ごみ"
  },
  {
    "name": "封筒",
    "category": "資源物（紙類）"
  },
  {
    "name": "風鈴",
    "category": "破砕ごみ"
  },
  {
    "name": "フォーク（金属製）",
    "category": "資源物（金属類）"
  },
  {
    "name": "ふすま",
    "category": "破砕ごみ"
  },
  {
    "name": "ブックエンド（金属製）",
    "category": "資源物（金属類）"
  },
  {
    "name": "筆",
    "category": "可燃ごみ"
  },
  {
    "name": "ふとん",
    "category": "破砕ごみ"
  },
  {
    "name": "ふとんカバー",
    "category": "資源物（布・衣類）"
  },
  {
    "name": "ふとん乾燥機",
    "category": "資源物（小型家電）"
  },
  {
    "name": "フライパン",
    "category": "資源物（金属類）"
  },
  {
    "name": "ブラインド（プラスチック製）",
    "category": "破砕ごみ"
  },
  {
    "name": "プラスチックボトル（ペットボトルは除く）",
    "category": "可燃ごみ"
  },
  {
    "name": "プラスチック容器",
    "category": "可燃ごみ"
  },
  {
    "name": "プラモデル",
    "category": "可燃ごみ"
  },
  {
    "name": "ブランコ（幼児用）（金属製）",
    "category": "資源物（金属類）"
  },
  {
    "name": "プランター（木製）",
    "category": "可燃ごみ"
  },
  {
    "name": "ブリキ製品",
    "category": "資源物（金属類）"
  },
  {
    "name": "プリンター",
    "category": "資源物（小型家電）"
  },
  {
    "name": "ブルーシート",
    "category": "破砕ごみ"
  },
  {
    "name": "ブルーレイディスク",
    "category": "可燃ごみ"
  },
  {
    "name": "ブルーレイレコーダー（プレーヤー）",
    "category": "資源物（小型家電）"
  },
  {
    "name": "古着・古布",
    "category": "資源物（布・衣類）"
  },
  {
    "name": "フロッピーディスク",
    "category": "可燃ごみ"
  },
  {
    "name": "風呂敷（布製）",
    "category": "資源物（布・衣類）"
  },
  {
    "name": "風呂ぶた（プラスチック製）",
    "category": "破砕ごみ"
  },
  {
    "name": "風呂マット（浴室用）（プラスチック製）",
    "category": "破砕ごみ"
  },
  {
    "name": "文鎮（金属製）",
    "category": "資源物（金属類）"
  },
  {
    "name": "噴霧器",
    "category": "破砕ごみ"
  },
  {
    "name": "ヘアーブラシ（プラスチック製）",
    "category": "可燃ごみ"
  },
  {
    "name": "ヘアピン（金属製）",
    "category": "資源物（金属類）"
  },
  {
    "name": "ベッド",
    "category": "粗大ごみ指定品目"
  },
  {
    "name": "ペットボトル",
    "category": "ペットボトル"
  },
  {
    "name": "ペットボトルのキャップ、ラベル",
    "category": "可燃ごみ"
  },
  {
    "name": "ヘッドホン",
    "category": "資源物（小型家電）"
  },
  {
    "name": "ベビーカー",
    "category": "破砕ごみ"
  },
  {
    "name": "ベビーゲート",
    "category": "破砕ごみ"
  },
  {
    "name": "ヘルスメーター",
    "category": "資源物（小型家電）"
  },
  {
    "name": "ベルト",
    "category": "可燃ごみ"
  },
  {
    "name": "ヘルメット",
    "category": "破砕ごみ"
  },
  {
    "name": "ペンキ",
    "category": "市では収集・処理しません"
  },
  {
    "name": "便座（ウォシュレット等）",
    "category": "破砕ごみ"
  },
  {
    "name": "弁当箱（プラスチック製）",
    "category": "可燃ごみ"
  },
  {
    "name": "ホース",
    "category": "可燃ごみ"
  },
  {
    "name": "ホースリール",
    "category": "破砕ごみ"
  },
  {
    "name": "ボーリングのボール",
    "category": "破砕ごみ"
  },
  {
    "name": "ボール（スポーツ用品）",
    "category": "可燃ごみ"
  },
  {
    "name": "ボールペン",
    "category": "可燃ごみ"
  },
  {
    "name": "ホーロー鍋",
    "category": "資源物（金属類）"
  },
  {
    "name": "ほうき",
    "category": "破砕ごみ"
  },
  {
    "name": "帽子",
    "category": "資源物（布・衣類）"
  },
  {
    "name": "包帯",
    "category": "可燃ごみ"
  },
  {
    "name": "包丁（金属製）",
    "category": "資源物（金属類）"
  },
  {
    "name": "包丁研ぎ器",
    "category": "可燃ごみ"
  },
  {
    "name": "ボウル（台所用品）（金属製）",
    "category": "資源物（金属類）"
  },
  {
    "name": "木刀",
    "category": "破砕ごみ"
  },
  {
    "name": "歩行器（幼児用）",
    "category": "破砕ごみ"
  },
  {
    "name": "ポスター",
    "category": "資源物（紙類）"
  },
  {
    "name": "ポータブルトイレ",
    "category": "可燃ごみ"
  },
  {
    "name": "ボタン電池",
    "category": "資源物（乾電池・水銀体温計）"
  },
  {
    "name": "補聴器",
    "category": "資源物（小型家電）"
  },
  {
    "name": "ホッチキスの針",
    "category": "資源物（金属類）"
  },
  {
    "name": "ホッチキス",
    "category": "資源物（金属類）"
  },
  {
    "name": "ポット",
    "category": "資源物（小型家電）"
  },
  {
    "name": "ホットカーペット",
    "category": "資源物（小型家電）"
  },
  {
    "name": "ホットカーラー",
    "category": "資源物（小型家電）"
  },
  {
    "name": "ホットプレート",
    "category": "資源物（小型家電）"
  },
  {
    "name": "哺乳びん（プラスチック製）",
    "category": "可燃ごみ"
  },
  {
    "name": "哺乳びん（ガラス製）",
    "category": "破砕ごみ"
  },
  {
    "name": "ホームフリーザー",
    "category": "市では収集・処理しません"
  },
  {
    "name": "ポリタンク",
    "category": "破砕ごみ"
  },
  {
    "name": "ポリバケツ",
    "category": "可燃ごみ"
  },
  {
    "name": "ポリ袋",
    "category": "可燃ごみ"
  },
  {
    "name": "保冷剤",
    "category": "可燃ごみ"
  },
  {
    "name": "ホワイトボード",
    "category": "資源物（金属類）"
  },
  {
    "name": "本",
    "category": "資源物（紙類）"
  },
  {
    "name": "本棚",
    "category": "粗大ごみ指定品目"
  },
  {
    "name": "麻雀パイ",
    "category": "可燃ごみ"
  },
  {
    "name": "マイク",
    "category": "資源物（小型家電）"
  },
  {
    "name": "マウス（パソコン用）",
    "category": "資源物（小型家電）"
  },
  {
    "name": "巻尺（メジャー）",
    "category": "可燃ごみ"
  },
  {
    "name": "マグネット",
    "category": "可燃ごみ"
  },
  {
    "name": "まくら",
    "category": "可燃ごみ"
  },
  {
    "name": "マジックペン",
    "category": "可燃ごみ"
  },
  {
    "name": "マスク（布）",
    "category": "可燃ごみ"
  },
  {
    "name": "マット",
    "category": "可燃ごみ"
  },
  {
    "name": "マットレス",
    "category": "破砕ごみ"
  },
  {
    "name": "まな板",
    "category": "可燃ごみ"
  },
  {
    "name": "マニキュアのびん",
    "category": "破砕ごみ"
  },
  {
    "name": "魔法瓶",
    "category": "資源物（金属類）"
  },
  {
    "name": "マヨネーズの容器",
    "category": "可燃ごみ"
  },
  {
    "name": "丸太（太さ5cm以上）",
    "category": "破砕ごみ"
  },
  {
    "name": "万歩計",
    "category": "資源物（小型家電）"
  },
  {
    "name": "みかんなどを入れたネット",
    "category": "可燃ごみ"
  },
  {
    "name": "ミキサー",
    "category": "資源物（小型家電）"
  },
  {
    "name": "ミシン（足踏み式）",
    "category": "資源物（金属類）"
  },
  {
    "name": "ミシン（ポータブル）",
    "category": "資源物（小型家電）"
  },
  {
    "name": "耳かき",
    "category": "可燃ごみ"
  },
  {
    "name": "ミニコンポ",
    "category": "資源物（小型家電）"
  },
  {
    "name": "麦わら帽子",
    "category": "可燃ごみ"
  },
  {
    "name": "虫かご",
    "category": "可燃ごみ"
  },
  {
    "name": "蒸し器（金属製）",
    "category": "資源物（金属類）"
  },
  {
    "name": "虫めがね",
    "category": "破砕ごみ"
  },
  {
    "name": "めがね（金属製）",
    "category": "資源物（金属類）"
  },
  {
    "name": "目玉クリップ",
    "category": "資源物（金属類）"
  },
  {
    "name": "毛布",
    "category": "資源物（布・衣類）"
  },
  {
    "name": "木片",
    "category": "可燃ごみ"
  },
  {
    "name": "餅つき機",
    "category": "資源物（小型家電）"
  },
  {
    "name": "モップ（柄付モップ）",
    "category": "破砕ごみ"
  },
  {
    "name": "モデルガン",
    "category": "可燃ごみ"
  },
  {
    "name": "モニター（パソコン用）",
    "category": "資源物（小型家電）"
  },
  {
    "name": "物干し竿（金属製）",
    "category": "資源物（金属類）"
  },
  {
    "name": "物干し竿（プラスチック製）",
    "category": "破砕ごみ"
  },
  {
    "name": "物干し台（金属製）",
    "category": "資源物（金属類）"
  },
  {
    "name": "物干し台（コンクリート製の土台）",
    "category": "破砕ごみ"
  },
  {
    "name": "モバイルバッテリー",
    "category": "資源物（乾電池・水銀体温計）"
  },
  {
    "name": "やかん",
    "category": "資源物（金属類）"
  },
  {
    "name": "野菜くず",
    "category": "可燃ごみ"
  },
  {
    "name": "やすり（金属製）",
    "category": "資源物（金属類）"
  },
  {
    "name": "浴衣",
    "category": "資源物（布・衣類）"
  },
  {
    "name": "湯たんぽ（金属製）",
    "category": "資源物（金属類）"
  },
  {
    "name": "湯沸器（台所用）（金属製）",
    "category": "資源物（金属類）"
  },
  {
    "name": "浴槽",
    "category": "市では収集しません"
  },
  {
    "name": "よしず",
    "category": "破砕ごみ"
  },
  {
    "name": "ライター",
    "category": "資源物（ライター）"
  },
  {
    "name": "ラグマット",
    "category": "破砕ごみ"
  },
  {
    "name": "ラケット",
    "category": "破砕ごみ"
  },
  {
    "name": "ラジオ、ラジカセ",
    "category": "資源物（小型家電）"
  },
  {
    "name": "ラップ",
    "category": "可燃ごみ"
  },
  {
    "name": "ランチジャー",
    "category": "可燃ごみ"
  },
  {
    "name": "ランドセル",
    "category": "可燃ごみ"
  },
  {
    "name": "ランプ（金属製）",
    "category": "資源物（金属類）"
  },
  {
    "name": "リール（釣具）（金属製）",
    "category": "資源物（金属類）"
  },
  {
    "name": "リコーダー（笛）",
    "category": "可燃ごみ"
  },
  {
    "name": "リモコン",
    "category": "資源物（小型家電）"
  },
  {
    "name": "リヤカー",
    "category": "市では収集しません"
  },
  {
    "name": "リュックサック",
    "category": "可燃ごみ"
  },
  {
    "name": "リンスの容器",
    "category": "可燃ごみ"
  },
  {
    "name": "ルーズリーフ",
    "category": "資源物（紙類）"
  },
  {
    "name": "ルームランナー",
    "category": "粗大ごみ指定品目"
  },
  {
    "name": "冷蔵庫・冷凍庫",
    "category": "市では収集・処理しません"
  },
  {
    "name": "冷暖房器具（エアコン）",
    "category": "市では収集・処理しません"
  },
  {
    "name": "冷風機",
    "category": "資源物（小型家電）"
  },
  {
    "name": "レコード盤",
    "category": "可燃ごみ"
  },
  {
    "name": "レジ袋",
    "category": "可燃ごみ"
  },
  {
    "name": "レジャーシート",
    "category": "可燃ごみ"
  },
  {
    "name": "レトルトパック",
    "category": "可燃ごみ"
  },
  {
    "name": "れんが",
    "category": "破砕ごみ"
  },
  {
    "name": "レンジフードフィルター（不織布）",
    "category": "可燃ごみ"
  },
  {
    "name": "ローソク",
    "category": "可燃ごみ"
  },
  {
    "name": "ロープ",
    "category": "可燃ごみ"
  },
  {
    "name": "ローボード",
    "category": "粗大ごみ指定品目"
  },
  {
    "name": "ローラースケート",
    "category": "可燃ごみ"
  },
  {
    "name": "ろう引き紙",
    "category": "可燃ごみ"
  },
  {
    "name": "ロッカー（金属製）",
    "category": "資源物（金属類）"
  },
  {
    "name": "ワープロ",
    "category": "資源物（小型家電）"
  },
  {
    "name": "ワイパー（ゴム製）",
    "category": "可燃ごみ"
  },
  {
    "name": "ワインセラー",
    "category": "市では収集・処理しません"
  },
  {
    "name": "輪ゴム",
    "category": "可燃ごみ"
  },
  {
    "name": "綿【わた】",
    "category": "可燃ごみ"
  },
  {
    "name": "綿入れ半纏【はんてん】",
    "category": "資源物（布・衣類）"
  },
  {
    "name": "ワックスの缶",
    "category": "資源物（金属類）"
  },
  {
    "name": "割りばし、割りばしの袋",
    "category": "可燃ごみ"
  }
]